LICENSE
MANIFEST.in
README.rst
setup.cfg
setup.py
pangocairocffi/VERSION
pangocairocffi/__init__.py
pangocairocffi/c_definitions_cairo.txt
pangocairocffi/c_definitions_glib.txt
pangocairocffi/c_definitions_pango.txt
pangocairocffi/c_definitions_pangocairo.txt
pangocairocffi/create_update_functions.py
pangocairocffi/ffi_build.py
pangocairocffi/font_functions.py
pangocairocffi/font_map.py
pangocairocffi/render_functions.py
pangocairocffi.egg-info/PKG-INFO
pangocairocffi.egg-info/SOURCES.txt
pangocairocffi.egg-info/dependency_links.txt
pangocairocffi.egg-info/requires.txt
pangocairocffi.egg-info/top_level.txt
pangocairocffi/_generated/ffi_pango.py