Metadata-Version: 2.1
Name: pangocairocffi
Version: 0.3.1
Summary: CFFI-based pango-cairo bindings for Python
Home-page: https://github.com/leifgehrmann/pangocairocffi
Author: Leif Gehrmann
License: LGPL-2.1
Project-URL: Code, https://github.com/leifgehrmann/pangocairocffi
Project-URL: Issue tracker, https://github.com/leifgehrmann/pangocairocffi/issues
Keywords: pango,cairo,cffi,binding
Platform: UNKNOWN
Classifier: Development Status :: 1 - Planning
Classifier: Intended Audience :: Developers
Classifier: Natural Language :: English
Classifier: Programming Language :: Python :: 3 :: Only
Classifier: Programming Language :: Python :: 3.5
Classifier: Programming Language :: Python :: 3.6
Classifier: Programming Language :: Python :: 3.7
Classifier: Programming Language :: Python :: 3.8
Classifier: Topic :: Multimedia :: Graphics
Classifier: Topic :: Text Processing :: Fonts
Requires-Python: >=3.5
